conc/__init__.py
conc/_modidx.py
conc/collocates.py
conc/conc.py
conc/concordance.py
conc/core.py
conc/corpora.py
conc/corpus.py
conc/frequency.py
conc/keyness.py
conc/listcorpus.py
conc/ngrams.py
conc/plot.py
conc/result.py
conc/text.py
conc-0.1.13.dist-info/licenses/LICENSE
conc-0.1.13.dist-info/METADATA
conc-0.1.13.dist-info/WHEEL
conc-0.1.13.dist-info/entry_points.txt
conc-0.1.13.dist-info/top_level.txt
conc-0.1.13.dist-info/RECORD
