Metadata-Version: 2.4
Name: conc
Version: 0.1.13
Summary: A Python library for efficient corpus analysis, enabling corpus linguistic analysis in Jupyter notebooks.
Home-page: https://github.com/polsci/conc
Author: polsci
Author-email: geoffrey.ford@canterbury.ac.nz
License: MIT License
Keywords: corpus corpora nbdev jupyter notebook python
Classifier: Development Status :: 4 - Beta
Classifier: Intended Audience :: Developers
Classifier: Natural Language :: English
Classifier: Programming Language :: Python :: 3.10
Classifier: Programming Language :: Python :: 3.11
Classifier: Programming Language :: Python :: 3.12
Classifier: License :: OSI Approved :: MIT License
Requires-Python: >=3.10
License-File: LICENSE
Requires-Dist: fastcore
Requires-Dist: numpy>=2.0.0
Requires-Dist: polars==1.31.0
Requires-Dist: scipy
Requires-Dist: msgspec
Requires-Dist: great_tables
Requires-Dist: spacy
Requires-Dist: python-slugify
Requires-Dist: plotly
Requires-Dist: jupyterlab
Requires-Dist: ipywidgets
Requires-Dist: memory_profiler
Requires-Dist: requests
Requires-Dist: lxml
Provides-Extra: dev
Requires-Dist: nbdev; extra == "dev"
Requires-Dist: line_profiler; extra == "dev"
Requires-Dist: nltk; extra == "dev"
Requires-Dist: datasets; extra == "dev"
Requires-Dist: jupyterlab-quarto; extra == "dev"
Requires-Dist: twine; extra == "dev"
Requires-Dist: pandas; extra == "dev"
Requires-Dist: pyarrow; extra == "dev"
Requires-Dist: matplotlib; extra == "dev"
Dynamic: author
Dynamic: author-email
Dynamic: classifier
Dynamic: description
Dynamic: description-content-type
Dynamic: home-page
Dynamic: keywords
Dynamic: license
Dynamic: license-file
Dynamic: provides-extra
Dynamic: requires-dist
Dynamic: requires-python
Dynamic: summary
